hello_proj/__init__.py
hello_proj/hello.py
hello_proj/web/__init__.py
hello_proj/web/hello_project/__init__.py
hello_proj/web/hello_project/asgi.py
hello_proj/web/hello_project/settings.py
hello_proj/web/hello_project/urls.py
hello_proj/web/hello_project/wsgi.py
hello_proj/web/manage.py
hello_proj-0.1.2.post4.dist-info/LICENSE.txt
hello_proj-0.1.2.post4.dist-info/METADATA
hello_proj-0.1.2.post4.dist-info/WHEEL
hello_proj-0.1.2.post4.dist-info/entry_points.txt
hello_proj-0.1.2.post4.dist-info/RECORD
