Metadata-Version: 2.3
Name: hello-proj
Version: 0.1.2.post4
Summary: Something
Author: AmirthanathanR
Author-email: amirth300324@gmail.com
Requires-Python: >=3.10
Classifier: Programming Language :: Python :: 3
Classifier: Programming Language :: Python :: 3.10
Classifier: Programming Language :: Python :: 3.11
Classifier: Programming Language :: Python :: 3.12
Classifier: Programming Language :: Python :: 3.13
Requires-Dist: django (>=5.2,<6.0)
Requires-Dist: gunicorn (>=23.0.0,<24.0.0)
